SSML
