Metadata-Version: 2.1
Name: SSML
Version: 1.0.8
Summary: This is a description
Home-page: https://github.com/Shinyhero36/SSML
Author: Shinyhero36
License: GNU General Public License v3.0
Project-URL: Source, https://github.com/Shinyhero36/SSML/
Project-URL: Tracker, https://github.com/Shinyhero36/SSML/issues
Keywords: ssml python google alexa assistant
Platform: UNKNOWN
Classifier: Development Status :: 3 - Alpha
Classifier: Intended Audience :: Developers
Classifier: Operating System :: OS Independent
Classifier: License :: OSI Approved :: GNU General Public License v3 (GPLv3)
Classifier: Programming Language :: Python
Classifier: Topic :: Home Automation
Requires-Python: >=3.6
License-File: LICENSE
